allophant-1.0.0.dist-info/METADATA
allophant-1.0.0.dist-info/WHEEL
allophant-1.0.0.dist-info/entry_points.txt
allophant-1.0.0.dist-info/licenses/LICENSE
allophant/phoneme_segmentation.py
allophant/__main__.py
allophant/get_attribute_error_rates.py
allophant/dataset_processing.py
allophant/package_data/default_dialects.json
allophant/package_data/LICENSE.txt
allophant/package_data/espeakng_phoneme_replacements.json
allophant/package_data/allophoible.csv
allophant/package_data/__init__.py
allophant/package_data/default_config.toml
allophant/phonemes.pyi
allophant/language_codes.py
allophant/phonetic_features.py
allophant/csv_validator.py
allophant/utils.py
allophant/evaluation.py
allophant/batching.py
allophant/attribute_graph.py
allophant/datasets/__main__.py
allophant/datasets/mozilla_common_voice.py
allophant/datasets/phonemes.py
allophant/datasets/ucla_phonetic_corpus.py
allophant/datasets/speech_corpus.py
allophant/datasets/__init__.py
allophant/datasets/corpus_loading.py
allophant/network/padding.py
allophant/network/frontend.py
allophant/network/acoustic_model.py
allophant/network/__init__.py
allophant/run.py
allophant/estimator.py
allophant/preprocessing.py
allophant/loss_functions.py
allophant/predictions.py
allophant/config.py
allophant/__init__.py
allophant/phonemes.cpython-310-darwin.so
allophant-1.0.0.dist-info/RECORD
