Metadata-Version: 2.3
Name: allophant
Version: 1.0.0
Classifier: Intended Audience :: Science/Research
Classifier: Topic :: Scientific/Engineering :: Artificial Intelligence
Classifier: Topic :: Multimedia :: Sound/Audio :: Speech
Classifier: Development Status :: 5 - Production/Stable
Classifier: Environment :: Console
Classifier: Environment :: GPU :: NVIDIA CUDA
Classifier: Programming Language :: Python :: 3.10
Classifier: Programming Language :: Python :: 3.11
Classifier: Programming Language :: Python :: 3.12
Classifier: Programming Language :: Rust
Classifier: Operating System :: OS Independent
Requires-Dist: tensorboard >=2.11.0
Requires-Dist: torch >=2.3.1
Requires-Dist: torchaudio >=2.3.1
Requires-Dist: marshmallow ==3.18.0
Requires-Dist: marshmallow-enum ==1.5.1
Requires-Dist: marshmallow-oneofschema ==3.0.1
Requires-Dist: toml ==0.10.2
Requires-Dist: numpy ==1.26.4
Requires-Dist: transformers ==4.41.2
Requires-Dist: stanza ==1.4.2
Requires-Dist: epitran ==1.23
Requires-Dist: phonemizer ==3.2.1
Requires-Dist: langcodes[data] ==3.3.0
Requires-Dist: marshmallow-dataclass[enum,union] ==8.7.1
Requires-Dist: pandas ==1.5.3
Requires-Dist: requests ==2.28.1
Requires-Dist: tqdm ==4.64.1
Requires-Dist: panphon ==0.20.0
Requires-Dist: msgpack ==1.0.4
Requires-Dist: mutagen ==1.45.1
Requires-Dist: zarr ==2.13.3
Requires-Dist: mashumaro[msgpack] ==3.7
Requires-Dist: regex ==2022.10.31
Requires-Dist: flashlight-text ==0.0.7
License-File: LICENSE
Summary: A multilingual phoneme recognizer capable of generalizing zero-shot to unseen phoneme inventories.
Author: Kevin Glocker <kevin.glocker@liu.se>
Author-email: Kevin Glocker <kevin.glocker@liu.se>, Aaricia Herygers <aariciaherygers@gmail.com>
Requires-Python: >=3.10
Project-URL: source, https://github.com/kgnlp/allophant
